publish_sphinx_docs/__init__.py
publish_sphinx_docs/main.py
publish_sphinx_docs-1.1.0.dist-info/METADATA
publish_sphinx_docs-1.1.0.dist-info/WHEEL
publish_sphinx_docs-1.1.0.dist-info/entry_points.txt
publish_sphinx_docs-1.1.0.dist-info/RECORD
