Metadata-Version: 2.4
Name: publish-sphinx-docs
Version: 1.1.0
Summary: A simple Python CLI to publish your Sphinx documentation to a Github Pages or Gitlab Pages repository.
Author-email: Alexander Raichev <araichev@mrcagney.com>
License-Expression: MIT
Requires-Python: >=3.10
Requires-Dist: click>=8
Requires-Dist: ghp-import>=1
